copra/agent/__init__.py
copra/agent/dfs_hammer_policy_prompter.py
copra/agent/dfs_policy_prompter.py
copra/agent/dfs_tree_search_with_stack.py
copra/agent/gpt_guided_tree_search_policy.py
copra/agent/handle_have_tactic.py
copra/agent/human_policy.py
copra/agent/rate_limiter.py
copra/agent/simple_policy_prompter.py
copra/agent/simple_proof_agent.py
copra/agent/simple_string_policy_prompter.py
copra/baselines/gpt4/__init__.py
copra/baselines/gpt4/few_shot_grammar.py
copra/baselines/gpt4/few_shot_policy.py
copra/baselines/gpt4/few_shot_policy_prompter.py
copra/baselines/gpt4/hammer_policy_prompter.py
copra/baselines/gpt4/informal_few_shot_grammar.py
copra/baselines/gpt4/informal_few_shot_policy.py
copra/baselines/gpt4/informal_few_shot_policy_prompter.py
copra/gpts/__init__.py
copra/gpts/gpt_access.py
copra/gpts/llama2_chat_format.py
copra/gpts/llama_access.py
copra/gpts/start_llama.sh
copra/main/__init__.py
copra/main/checkpoint_manager.py
copra/main/config.py
copra/main/eval_benchmark.py
copra/main/lemma_discovery.py
copra/main/parallel_execution.py
copra/main/parallel_theorem_execution.py
copra/main/policy_factory.py
copra/main/proof_execution.py
copra/main/run.py
copra/main/stats.py
copra/main/config/coq_experiments.yaml
copra/main/config/experiments.yaml
copra/main/config/lean4_simple_experiment.yaml
copra/main/config/lean4_simple_experiment_few_shot.yaml
copra/main/config/lean4_simple_experiment_few_shot_kimina.yaml
copra/main/config/lean4_simple_experiment_open_source.yaml
copra/main/config/miniF2F_lean4_easy_to_hard_gpt_oss.yaml
copra/main/config/miniF2F_lean4_imo_experiments.yaml
copra/main/config/stack_machine_lean_experiments.yaml
copra/main/config/benchmark/agent_proverbot_hard.yaml
copra/main/config/benchmark/compcert_118_subset.yaml
copra/main/config/benchmark/compcert_benchmark.yaml
copra/main/config/benchmark/compcert_benchmark_hard.yaml
copra/main/config/benchmark/compcert_benchmark_hard_1.yaml
copra_theorem_prover-1.5.0.dist-info/METADATA
copra_theorem_prover-1.5.0.dist-info/WHEEL
copra_theorem_prover-1.5.0.dist-info/entry_points.txt
copra_theorem_prover-1.5.0.dist-info/RECORD
