Metadata-Version: 2.4
Name: copra-theorem-prover
Version: 1.5.0
Summary: Python library for running proof search using CoPra
Project-URL: Homepage, https://github.com/trishullab/copra
Project-URL: Issues, https://github.com/trishullab/copra/issues
Author-email: Amitayush Thakur <amitayush@utexas.edu>
Classifier: License :: OSI Approved :: MIT License
Classifier: Operating System :: POSIX :: Linux
Classifier: Programming Language :: Python :: 3
Requires-Python: >=3.9
Requires-Dist: boto3==1.38.14
Requires-Dist: huggingface-hub<0.32,>=0.30; python_version >= '3.14'
Requires-Dist: huggingface-hub<1.0,>=0.34; python_version < '3.13'
Requires-Dist: itp-interface>=1.5.0
Requires-Dist: numpy>=2.1.0
Requires-Dist: openai>=1.99.1
Requires-Dist: pydantic>=2.12.0
Requires-Dist: requests>=2.32.0
Requires-Dist: sentencepiece>=0.2.0
Requires-Dist: tiktoken>=0.12.0
Requires-Dist: transformers<4.54,>=4.48; python_version >= '3.14'
Requires-Dist: transformers>=4.56; python_version < '3.13'
Provides-Extra: gpt-oss
Requires-Dist: vllm==0.10.2; extra == 'gpt-oss'
Provides-Extra: os-models
Requires-Dist: vllm>=0.11.0; (python_version < '3.13') and extra == 'os-models'
Provides-Extra: ui
Requires-Dist: gradio<5.50,>=4.0.0; extra == 'ui'
